{"name":"软件","postlist":[{"title":"Windows 修改默认安装路径","slug":"14","date":"2022-12-24T18:55:00.000Z","updated":"2024-07-02T13:13:11.243Z","comments":null,"path":"api/articles/14.json","excerpt":null,"keywords":null,"cover":null,"content":null,"raw":null,"categories":[{"name":"实用教程","path":"api/categories/实用教程.json"},{"name":"Windows","path":"api/categories/Windows.json"}],"tags":[{"name":"Windows","path":"api/tags/Windows.json"},{"name":"系统","path":"api/tags/系统.json"},{"name":"Software","path":"api/tags/Software.json"},{"name":"软件","path":"api/tags/软件.json"}]}]}